voiceflow_module/__init__.py
voiceflow_module/ai_service.py
voiceflow_module/kb_manager.py
voiceflow_module/utils.py
voiceflow_module-0.5.1.dist-info/METADATA
voiceflow_module-0.5.1.dist-info/WHEEL
voiceflow_module-0.5.1.dist-info/top_level.txt
voiceflow_module-0.5.1.dist-info/RECORD
